{"gtabs":[{"panes":[{"ptabs":[{"history":[{"dir":"/home/jacob","file":"Documents","relpos":2,"ts":1608316969},{"dir":"/home/jacob/Documents","file":"..","relpos":0,"ts":1608317043},{"dir":"/home/jacob","file":"Downloads","relpos":3,"ts":1608317043},{"dir":"/home/jacob/Downloads","file":"..","relpos":0,"ts":1608317043},{"dir":"/home/jacob","file":"Downloads","relpos":3,"ts":1608317043},{"dir":"/home","file":"..","relpos":0,"ts":1608317043}],"filters":{"invert":true,"dot":true,"manual":"","auto":""},"last-location":"/home","sorting":[2],"preview":false}]},{"ptabs":[{"history":[{"dir":"/home/jacob","file":"Pictures","relpos":5,"ts":1608316969},{"dir":"/home/jacob/Pictures","file":"Backgrounds","relpos":1,"ts":1608317043},{"dir":"/home/jacob/Pictures/Backgrounds","file":"491792.jpg","relpos":1,"ts":1608317043}],"filters":{"invert":true,"dot":true,"manual":"","auto":""},"last-location":"/home/jacob/Pictures/Backgrounds","sorting":[2],"preview":false}]}],"active-pane":1,"preview":false,"splitter":{"pos":-1,"ratio":0.5,"orientation":"v","expanded":false}}],"marks":{"H":{"dir":"/home/jacob/","file":"..","ts":1608316964},"b":{"dir":"/home/jacob/bin/","file":"..","ts":1608316964},"h":{"dir":"/home/jacob/","file":"..","ts":1608316964},"z":{"dir":"/home/jacob/.config/vifm","file":"..","ts":1608316964}},"bmarks":{},"cmd-hist":[{"text":"!feh 491792.jpg","ts":1608317079}],"regs":{},"dir-stack":[],"use-term-multiplexer":false}